odoo/addons/report_qweb_txt/README.rst
odoo/addons/report_qweb_txt/__init__.py
odoo/addons/report_qweb_txt/__manifest__.py
odoo/addons/report_qweb_txt/demo/report.xml
odoo/addons/report_qweb_txt/demo/res_users_report.xml
odoo/addons/report_qweb_txt/i18n/ca.po
odoo/addons/report_qweb_txt/i18n/da.po
odoo/addons/report_qweb_txt/i18n/de.po
odoo/addons/report_qweb_txt/i18n/el_GR.po
odoo/addons/report_qweb_txt/i18n/es.po
odoo/addons/report_qweb_txt/i18n/es_CO.po
odoo/addons/report_qweb_txt/i18n/fr.po
odoo/addons/report_qweb_txt/i18n/gl.po
odoo/addons/report_qweb_txt/i18n/hr.po
odoo/addons/report_qweb_txt/i18n/hr_HR.po
odoo/addons/report_qweb_txt/i18n/it.po
odoo/addons/report_qweb_txt/i18n/nb_NO.po
odoo/addons/report_qweb_txt/i18n/nl_NL.po
odoo/addons/report_qweb_txt/i18n/pl.po
odoo/addons/report_qweb_txt/i18n/pt.po
odoo/addons/report_qweb_txt/i18n/pt_BR.po
odoo/addons/report_qweb_txt/i18n/pt_PT.po
odoo/addons/report_qweb_txt/i18n/report_qweb_txt.pot
odoo/addons/report_qweb_txt/i18n/sl.po
odoo/addons/report_qweb_txt/i18n/tr.po
odoo/addons/report_qweb_txt/i18n/tr_TR.po
odoo/addons/report_qweb_txt/models/__init__.py
odoo/addons/report_qweb_txt/models/ir_actions_report.py
odoo/addons/report_qweb_txt/readme/CONTRIBUTORS.rst
odoo/addons/report_qweb_txt/readme/DESCRIPTION.rst
odoo/addons/report_qweb_txt/readme/USAGE.rst
odoo/addons/report_qweb_txt/static/description/icon.png
odoo/addons/report_qweb_txt/static/description/index.html
odoo11_addon_report_qweb_txt-11.0.1.0.0.99.dev4.dist-info/METADATA
odoo11_addon_report_qweb_txt-11.0.1.0.0.99.dev4.dist-info/WHEEL
odoo11_addon_report_qweb_txt-11.0.1.0.0.99.dev4.dist-info/top_level.txt
odoo11_addon_report_qweb_txt-11.0.1.0.0.99.dev4.dist-info/RECORD
